rac_schema_validator/__init__.py
rac_schema_validator/exceptions.py
rac_schema_validator-1.0.dist-info/LICENSE
rac_schema_validator-1.0.dist-info/METADATA
rac_schema_validator-1.0.dist-info/WHEEL
rac_schema_validator-1.0.dist-info/top_level.txt
rac_schema_validator-1.0.dist-info/RECORD
