Metadata-Version: 2.1
Name: rac_schema_validator
Version: 1.0
Summary: Validator for RAC JSON Schemas
Home-page: http://github.com/RockefellerArchiveCenter/rac_schema_validator
Author: Rockefeller Archive Center
Author-email: archive@rockarch.org
License: MIT
Classifier: Programming Language :: Python :: 3
Classifier: License :: OSI Approved :: MIT License
Classifier: Operating System :: OS Independent
Requires-Python: >=3.10
License-File: LICENSE
Requires-Dist: jsonschema
